pretf/api.py
pretf/blocks.py
pretf/cli.py
pretf/collections.py
pretf/exceptions.py
pretf/labels.py
pretf/log.py
pretf/parser.py
pretf/render.py
pretf/test.py
pretf/util.py
pretf/variables.py
pretf/version.py
pretf/workflow.py
pretf-0.7.3.dist-info/METADATA
pretf-0.7.3.dist-info/WHEEL
pretf-0.7.3.dist-info/entry_points.txt
pretf-0.7.3.dist-info/top_level.txt
pretf-0.7.3.dist-info/RECORD
