Metadata-Version: 2.1
Name: pretf
Version: 0.7.3
Summary: UNKNOWN
Home-page: UNKNOWN
Author: Raymond Butcher
Author-email: ray.butcher@claranet.uk
License: MIT License
Platform: UNKNOWN
Requires-Python: >=3.6
Requires-Dist: colorama
Requires-Dist: pyhcl
Requires-Dist: pytest
Provides-Extra: aws
Requires-Dist: pretf.aws (==0.7.3) ; extra == 'aws'
